odoo8_addon_website_sale_cart_preview-8.0.1.0.0.99.dev13-py2.7-nspkg.pth
odoo8_addon_website_sale_cart_preview-8.0.1.0.0.99.dev13.dist-info/METADATA
odoo8_addon_website_sale_cart_preview-8.0.1.0.0.99.dev13.dist-info/RECORD
odoo8_addon_website_sale_cart_preview-8.0.1.0.0.99.dev13.dist-info/WHEEL
odoo8_addon_website_sale_cart_preview-8.0.1.0.0.99.dev13.dist-info/namespace_packages.txt
odoo8_addon_website_sale_cart_preview-8.0.1.0.0.99.dev13.dist-info/top_level.txt
odoo_addons/website_sale_cart_preview/README.rst
odoo_addons/website_sale_cart_preview/__init__.py
odoo_addons/website_sale_cart_preview/__openerp__.py
odoo_addons/website_sale_cart_preview/controllers/__init__.py
odoo_addons/website_sale_cart_preview/controllers/main.py
odoo_addons/website_sale_cart_preview/i18n/bg.po
odoo_addons/website_sale_cart_preview/i18n/ca.po
odoo_addons/website_sale_cart_preview/i18n/de.po
odoo_addons/website_sale_cart_preview/i18n/el_GR.po
odoo_addons/website_sale_cart_preview/i18n/es.po
odoo_addons/website_sale_cart_preview/i18n/eu.po
odoo_addons/website_sale_cart_preview/i18n/fr.po
odoo_addons/website_sale_cart_preview/i18n/it.po
odoo_addons/website_sale_cart_preview/i18n/nl_NL.po
odoo_addons/website_sale_cart_preview/i18n/pt_BR.po
odoo_addons/website_sale_cart_preview/i18n/ru.po
odoo_addons/website_sale_cart_preview/i18n/sl.po
odoo_addons/website_sale_cart_preview/static/description/icon.png
odoo_addons/website_sale_cart_preview/static/src/css/website_sale_cart_preview.css
odoo_addons/website_sale_cart_preview/static/src/js/website_sale_cart_preview.js
odoo_addons/website_sale_cart_preview/templates/website.xml
odoo_addons/website_sale_cart_preview/templates/website_sale.xml
odoo_addons/website_sale_cart_preview/templates/website_sale_cart_preview.xml
